nashi_ocr/__init__.py
nashi_ocr/nashi_client.py
nashi_ocr-0.4.2.dist-info/LICENSE
nashi_ocr-0.4.2.dist-info/METADATA
nashi_ocr-0.4.2.dist-info/WHEEL
nashi_ocr-0.4.2.dist-info/top_level.txt
nashi_ocr-0.4.2.dist-info/RECORD
