Metadata-Version: 2.1
Name: nashi-ocr
Version: 0.4.2
Summary: An OCR client complementing webapp for the transcription of scanned pages
Home-page: https://github.com/andbue/nashi
Author: Andreas Büttner
Author-email: andreas.buettner@uni-wuerzburg.de
License: GPL_v3.0
Platform: UNKNOWN
Classifier: Programming Language :: Python :: 3
Classifier: Development Status :: 3 - Alpha
Classifier: License :: OSI Approved :: GNU General Public License v3 (GPLv3)
Requires-Python: >=3
Requires-Dist: requests
Requires-Dist: h5py
Requires-Dist: numpy
Requires-Dist: lxml
Requires-Dist: calamari-ocr (>=2.1.1)
